[{"name":"111","surname":"111","login":"111","phone":"111","email":"111","dob":"1111-11-11","password":"111"},{"name":"9","surname":"9","login":"9","phone":"9","email":"9","dob":"1111-09-09","password":"9"},{"name":"1","surname":"1","login":"1","phone":"1","email":"1","dob":"0001-01-01","password":"1"},{"name":"77","surname":"77","login":"77","phone":"77","email":"77","dob":"2222-07-07","password":"77"},{"name":"22","surname":"33","login":"3","phone":"33","email":"3","dob":"1111-03-31","password":"3"},{"name":"12","surname":"12","login":"12","phone":"12","email":"12","dob":"1222-12-12","password":"12"}]